slipstream_cli-0.8.2-py2.7-nspkg.pth
slipstream/cli/__init__.py
slipstream/cli/base.py
slipstream/cli/commands.py
slipstream/cli/conf.py
slipstream/cli/log.py
slipstream/cli/types.py
slipstream_cli-0.8.2.dist-info/DESCRIPTION.rst
slipstream_cli-0.8.2.dist-info/METADATA
slipstream_cli-0.8.2.dist-info/RECORD
slipstream_cli-0.8.2.dist-info/WHEEL
slipstream_cli-0.8.2.dist-info/entry_points.txt
slipstream_cli-0.8.2.dist-info/metadata.json
slipstream_cli-0.8.2.dist-info/namespace_packages.txt
slipstream_cli-0.8.2.dist-info/top_level.txt
